vg_exec/__init__.py
vg_exec/create_vhost.py
vg_exec/remove_vhost.py
vg_lib/__init__.py
vg_lib/raw/__init__.py
vg_lib/raw/util/__init__.py
vg_lib/raw/util/config.py
vg_lib/raw/util/device.py
vg_lib/raw/util/domain.py
vg_lib/raw/util/email.py
vg_lib/raw/util/errors.py
vg_lib/raw/util/files.py
vg_lib/raw/util/hashing.py
vg_lib/raw/util/ip.py
vg_lib/raw/util/libs.py
vg_lib/raw/util/selinux.py
vg_lib/raw/util/systemd.py
vg_lib/raw/util/types.py
vg_lib/raw/util/user.py
vg_lib/raw/vhost/__init__.py
vg_lib/raw/vhost/apache.py
vg_lib/raw/vhost/config.py
vg_lib/raw/vhost/cron.py
vg_lib/raw/vhost/defaults.py
vg_lib/raw/vhost/letsencrypt.py
vg_lib/raw/vhost/logging.py
vg_lib/raw/vhost/user.py
vg_lib/raw/vhost/virtualhost.py
vg_lib/templates/__init__.py
vg_lib/templates/apache_virtualhost.conf
vg_lib/templates/banner_sftp.txt
vg_lib/templates/php-fpm-pool.conf
vg_lib/templates/rsyslog.conf
vg_lib/templates/vh_cron.sh
vg_management-0.1.0.post3.dist-info/licenses/LICENSE
vg_management-0.1.0.post3.dist-info/METADATA
vg_management-0.1.0.post3.dist-info/WHEEL
vg_management-0.1.0.post3.dist-info/entry_points.txt
vg_management-0.1.0.post3.dist-info/top_level.txt
vg_management-0.1.0.post3.dist-info/RECORD
