Metadata-Version: 2.4
Name: vg_management
Version: 0.1.0.post3
Summary: The Python script & library for managing web service stack
Author-email: swettoth0812 <tan@vnguru.com>
License-Expression: Apache-2.0
Requires-Python: >=3.10
License-File: LICENSE
Requires-Dist: cryptography>=41.0.7
Requires-Dist: jinja2==3.1.2
Requires-Dist: markupsafe==2.1.3
Requires-Dist: netifaces>=0.10.0
Requires-Dist: pip==23.3.1
Requires-Dist: pyopenssl==23.3.0
Requires-Dist: pyyaml==6.0.1
Requires-Dist: setuptools==69.0.2
Requires-Dist: dnspython>=2.0.0
Dynamic: license-file
